[{"code": "2308", "turnover": 29324401945.0}, {"code": "2408", "turnover": 27126072238.0}, {"code": "3037", "turnover": 20788674118.0}, {"code": "2337", "turnover": 20334780153.0}, {"code": "2344", "turnover": 19877321592.0}, {"code": "2317", "turnover": 18947499607.0}, {"code": "6770", "turnover": 17374487036.0}, {"code": "1303", "turnover": 13178138965.0}, {"code": "2313", "turnover": 12372158884.0}, {"code": "6669", "turnover": 10948483380.0}, {"code": "3481", "turnover": 10779622155.0}, {"code": "2327", "turnover": 10153621932.0}, {"code": "2303", "turnover": 9035386576.0}, {"code": "2449", "turnover": 8837635801.0}, {"code": "2301", "turnover": 7243914244.0}, {"code": "2367", "turnover": 7098214246.0}, {"code": "7769", "turnover": 6937589260.0}, {"code": "6285", "turnover": 6925527947.0}, {"code": "1802", "turnover": 6882041082.0}, {"code": "3189", "turnover": 6714398389.0}, {"code": "4958", "turnover": 6078992028.0}, {"code": "2455", "turnover": 4890552442.0}, {"code": "2887", "turnover": 4542070916.0}, {"code": "2360", "turnover": 4416603125.0}, {"code": "2891", "turnover": 4097272432.0}, {"code": "3450", "turnover": 3888131600.0}, {"code": "2882", "turnover": 3639348943.0}, {"code": "2881", "turnover": 3529154387.0}, {"code": "6239", "turnover": 3501433670.0}, {"code": "2883", "turnover": 3475923296.0}, {"code": "2603", "turnover": 3388333633.0}, {"code": "3006", "turnover": 3282173043.0}, {"code": "2404", "turnover": 3204793561.0}, {"code": "3167", "turnover": 3057319645.0}, {"code": "3008", "turnover": 2865885045.0}, {"code": "8046", "turnover": 2842406215.0}, {"code": "2412", "turnover": 2775004024.0}, {"code": "1560", "turnover": 2672328166.0}, {"code": "8033", "turnover": 2622062128.0}, {"code": "8021", "turnover": 2547079200.0}, {"code": "2884", "turnover": 2489353055.0}, {"code": "3036", "turnover": 2300260972.0}, {"code": "2885", "turnover": 2274542805.0}, {"code": "8110", "turnover": 2138380050.0}, {"code": "6442", "turnover": 2004679405.0}, {"code": "2609", "turnover": 1917860308.0}, {"code": "6139", "turnover": 1838719773.0}, {"code": "2890", "turnover": 1838297374.0}, {"code": "6415", "turnover": 1832245432.0}, {"code": "6271", "turnover": 1805415437.0}]